FIAS_RU/__init__.py
FIAS_RU/SPAS/__init__.py
FIAS_RU/SPAS/base.py
FIAS_RU/SPAS/client.py
FIAS_RU/SPAS/exceptions.py
FIAS_RU/SPAS/models.py
fias_ru-0.1.2.dist-info/licenses/LICENSE
fias_ru-0.1.2.dist-info/METADATA
fias_ru-0.1.2.dist-info/WHEEL
fias_ru-0.1.2.dist-info/top_level.txt
fias_ru-0.1.2.dist-info/RECORD
