Metadata-Version: 2.4
Name: FIAS-RU
Version: 0.1.2
Summary: Простой и надёжный SDK для работы с ФИАС API
Author-email: Eclips team <develop@eclips-team.ru>
License: MIT
Project-URL: Homepage, https://github.com/PrimeevolutionZ/FIAS_RU
Project-URL: Documentation, https://github.com/PrimeevolutionZ/FIAS_RU#readme
Project-URL: Repository, https://github.com/PrimeevolutionZ/FIAS_RU
Project-URL: Issues, https://github.com/PrimeevolutionZ/FIAS_RU/issues
Keywords: fias,api,sdk,address,russia,фиас,адреса,geocoding,autocomplete
Classifier: Development Status :: 4 - Beta
Classifier: Intended Audience :: Developers
Classifier: License :: OSI Approved :: MIT License
Classifier: Programming Language :: Python :: 3
Classifier: Programming Language :: Python :: 3.9
Classifier: Programming Language :: Python :: 3.10
Classifier: Programming Language :: Python :: 3.11
Classifier: Programming Language :: Python :: 3.12
Classifier: Topic :: Software Development :: Libraries :: Python Modules
Classifier: Topic :: Internet :: WWW/HTTP
Classifier: Topic :: Software Development :: Libraries
Classifier: Operating System :: OS Independent
Classifier: Typing :: Typed
Requires-Python: >=3.8
License-File: LICENSE
Requires-Dist: httpx>=0.25.0
Requires-Dist: pydantic>=2.0.0
Provides-Extra: dev
Requires-Dist: pytest>=7.0.0; extra == "dev"
Requires-Dist: pytest-asyncio>=0.21.0; extra == "dev"
Requires-Dist: pytest-cov>=4.0.0; extra == "dev"
Requires-Dist: black>=23.0.0; extra == "dev"
Requires-Dist: mypy>=1.0.0; extra == "dev"
Requires-Dist: ruff>=0.1.0; extra == "dev"
Dynamic: license-file
